openapi_client/__init__.py
openapi_client/api_client.py
openapi_client/configuration.py
openapi_client/exceptions.py
openapi_client/rest.py
openapi_client/api/__init__.py
openapi_client/api/default_api.py
openapi_client/models/__init__.py
openapi_client/models/http_validation_error.py
openapi_client/models/speaker_id.py
openapi_client/models/tts_request.py
openapi_client/models/validation_error.py
parakeet/__init__.py
parakeet/api_client.py
parakeet/configuration.py
parakeet/exceptions.py
parakeet/rest.py
parakeet/api/__init__.py
parakeet/api/default_api.py
parakeet/models/__init__.py
parakeet/models/http_validation_error.py
parakeet/models/speaker_id.py
parakeet/models/tts_request.py
parakeet/models/validation_error.py
parakeet-python/__init__.py
parakeet-python/api_client.py
parakeet-python/configuration.py
parakeet-python/exceptions.py
parakeet-python/rest.py
parakeet-python/api/__init__.py
parakeet-python/api/default_api.py
parakeet-python/models/__init__.py
parakeet-python/models/http_validation_error.py
parakeet-python/models/speaker_id.py
parakeet-python/models/tts_request.py
parakeet-python/models/validation_error.py
parakeet_python-1.0.0.dist-info/METADATA
parakeet_python-1.0.0.dist-info/WHEEL
parakeet_python-1.0.0.dist-info/top_level.txt
parakeet_python-1.0.0.dist-info/RECORD
